jsonvalidatingschemaextractor/__init__.py
jsonvalidatingschemaextractor-0.1.0.dist-info/METADATA
jsonvalidatingschemaextractor-0.1.0.dist-info/WHEEL
jsonvalidatingschemaextractor-0.1.0.dist-info/RECORD
