Metadata-Version: 2.4
Name: jsonvalidatingschemaextractor
Version: 0.1.0
Summary: Validate and extract values from JSON objects using JSON schema.
Author: Fasih Khatib
Author-email: hellofasih.confound928@passinbox.com
Requires-Python: >=3.11
Classifier: Programming Language :: Python :: 3
Classifier: Programming Language :: Python :: 3.11
Classifier: Programming Language :: Python :: 3.12
Classifier: Programming Language :: Python :: 3.13
Classifier: Programming Language :: Python :: 3.14
Requires-Dist: jsonschema (>=4.25.1,<5.0.0)
Requires-Dist: pre-commit (>=4.3.0,<5.0.0)
